quart_cmark.py
Quart_Cmark-0.1.2.dist-info/LICENSE
Quart_Cmark-0.1.2.dist-info/METADATA
Quart_Cmark-0.1.2.dist-info/WHEEL
Quart_Cmark-0.1.2.dist-info/top_level.txt
Quart_Cmark-0.1.2.dist-info/RECORD
