Metadata-Version: 2.1
Name: Quart-Cmark
Version: 0.1.2
Summary: Add commonmark processing filter to your Quart app.
Home-page: https://gitlab.com/doug.shawhan/quart-cmark
Author: Doug Shawhan
Author-email: doug.shawhan@gmail.com
Maintainer: Doug Shawhan
Maintainer-email: doug.shawhan@gmail.com
License: Copyright 2019 Doug Shawhan        
Project-URL: Bug Tracker, https://gitlab.com/doug.shawhan/quart-cmark/issues
Project-URL: Source Code, https://gitlab.com/doug.shawhan/quart-cmark/tree/master
Project-URL: Development Version, https://gitlab.com/doug.shawhan/quart-cmark/tree/dev
Project-URL: Documentation, https://quart-cmark.readthedocs.io
Platform: any
Classifier: Development Status :: 5 - Production/Stable
Classifier: Environment :: Web Environment
Classifier: Intended Audience :: Developers
Classifier: License :: OSI Approved :: BSD License
Classifier: Operating System :: OS Independent
Classifier: Programming Language :: Python
Classifier: Programming Language :: Python :: 3.8
Classifier: Programming Language :: Python :: 3.9
Classifier: Programming Language :: Python :: 3.10
Classifier: Topic :: Internet :: WWW/HTTP :: Dynamic Content
Classifier: Topic :: Software Development :: Libraries :: Python Modules
License-File: LICENSE
Requires-Dist: Quart
Requires-Dist: jinja2 (>=3)
Requires-Dist: markupsafe (>=2)
Requires-Dist: paka.cmark (>=2.3.0)
